stackify/__init__.py
stackify/compat.py
stackify/config.py
stackify/constants.py
stackify/handler.py
stackify/handler_backport.py
stackify/rum.py
stackify/timer.py
stackify/utils.py
stackify/protos/__init__.py
stackify/protos/stackify_agent_pb2.py
stackify/transport/__init__.py
stackify/transport/application.py
stackify/transport/base.py
stackify/transport/agent/__init__.py
stackify/transport/agent/agent_http.py
stackify/transport/agent/agent_socket.py
stackify/transport/agent/message.py
stackify/transport/default/__init__.py
stackify/transport/default/error.py
stackify/transport/default/formats.py
stackify/transport/default/http.py
stackify/transport/default/log.py
stackify_api_python-1.2.0.dist-info/LICENSE.md
stackify_api_python-1.2.0.dist-info/METADATA
stackify_api_python-1.2.0.dist-info/WHEEL
stackify_api_python-1.2.0.dist-info/top_level.txt
stackify_api_python-1.2.0.dist-info/RECORD
