Metadata-Version: 2.1
Name: stackify-api-python
Version: 1.2.0
Summary: Stackify API for Python
Home-page: https://github.com/stackify/stackify-api-python
Author: Stackify
Author-email: support@stackify.com
License: UNKNOWN
Keywords: logging,stackify,exception
Platform: UNKNOWN
Classifier: Programming Language :: Python
Classifier: Programming Language :: Python :: 2.7
Classifier: Programming Language :: Python :: 3.4
Classifier: Programming Language :: Python :: 3.5
Classifier: Programming Language :: Python :: 3.6
Classifier: Programming Language :: Python :: 3.7
Classifier: Programming Language :: Python :: 3.8
Classifier: Programming Language :: Python :: Implementation :: CPython
Classifier: Programming Language :: Python :: Implementation :: PyPy
Classifier: Operating System :: OS Independent
Requires-Dist: protobuf (>=3.9.1)
Requires-Dist: retrying (>=1.2.3)
Requires-Dist: requests (>=2.4.1)
Requires-Dist: requests-unixsocket (>=0.2.0)
